readme_metrics/GetProjectBaseUrl.py
readme_metrics/Metrics.py
readme_metrics/MetricsApiConfig.py
readme_metrics/MetricsMiddleware.py
readme_metrics/PayloadBuilder.py
readme_metrics/ResponseInfoWrapper.py
readme_metrics/VerifyWebhook.py
readme_metrics/__init__.py
readme_metrics/django.py
readme_metrics/fastapi.py
readme_metrics/flask_readme.py
readme_metrics/publisher.py
readme_metrics/util.py
readme_metrics-3.4.0.dist-info/LICENSE
readme_metrics-3.4.0.dist-info/METADATA
readme_metrics-3.4.0.dist-info/WHEEL
readme_metrics-3.4.0.dist-info/top_level.txt
readme_metrics-3.4.0.dist-info/RECORD
