Metadata-Version: 2.1
Name: readme-metrics
Version: 3.4.0
Summary: ReadMe API Metrics SDK
Home-page: https://github.com/readmeio/metrics-sdks/tree/main/packages/python
Author: ReadMe
Author-email: support@readme.io
License-File: LICENSE
Requires-Dist: requests
Requires-Dist: Werkzeug
Provides-Extra: flask
Requires-Dist: Flask; extra == "flask"
Provides-Extra: django
Requires-Dist: Django; extra == "django"
